<?xml version="1.0" encoding="UTF-8"?>
<mets xmlns="http://www.loc.gov/METS/" xmlns:dc="http://purl.org/dc/elements/1.1/" xmlns:mods="http://www.loc.gov/mods/v3" xmlns:xlink="http://www.w3.org/1999/xlink" xmlns:xsi="http://www.w3.org/2001/XMLSchema-instance" xsi:schemaLocation="http://www.loc.gov/standards/mets/mets.xsd">
  <metsHdr CREATEDATE="2020-03-25 08:48:18 -0400">
    <agent ROLE="CREATOR" TYPE="ORGANIZATION">
      <name>Rockefeller Archive Center</name>
      <note>http://www.rockarch.org</note>
      <note>Produced by ArchivesSpace</note>
    </agent>
  </metsHdr>
  <dmdSec ID="2547">
    <mdWrap MDTYPE="MODS">
      <xmlData>
        <mods version="3.4" xmlns="http://www.loc.gov/mods/v3">
          <mods:titleInfo>
            <mods:title>Appleget_1935.pdf</mods:title>
          </mods:titleInfo>
          <mods:identifier type="local">dcfddb64-8d34-49f9-95fd-b46ce2e1b09f</mods:identifier>
          <mods:typeOfResource/>
          <mods:originInfo/>
          <mods:physicalDescription/>
          <mods:note type="originalsloc">885116ba-3432-4e01-a269-b87b06c33fc5</mods:note>
          <mods:note displayLabel="Digital object made available by">Rockefeller Archive Center, 15 Dayton Avenue, Sleepy Hollow, 10591, U.S.A. (http://www.rockarch.org)</mods:note>
          <mods:subject authority="lcsh">
            <mods:geographic>China</mods:geographic>
          </mods:subject>
          <mods:relatedItem displayLabel="resource" type="host">
            <mods:name>Rockefeller Foundation records, officers' diaries, RG 12, A-E</mods:name>
            <mods:identifier>FA391.xml</mods:identifier>
          </mods:relatedItem>
          <mods:relatedItem displayLabel="component" type="host">
            <mods:name>1935</mods:name>
            <mods:identifier>ad734c351a7f49678c8459534f384315</mods:identifier>
          </mods:relatedItem>
        </mods>
      </xmlData>
    </mdWrap>
  </dmdSec>
  <amdSec>
    <techMD ID="7421">
      <mdWrap MDTYPE="PREMIS:OBJECT">
        <xmlData>
          <object version="2.2" xmlns="info:lc/xmlns/premis-v2" xsi:schemaLocation="info:lc/xmlns/premis-v2 http://www.loc.gov/standards/premis/v2/premis-v2-2.xsd" xsi:type="file">
            <objectIdentifier>
              <objectIdentifierType>ArchivesSpace identifier</objectIdentifierType>
              <objectIdentifierValue>7421</objectIdentifierValue>
            </objectIdentifier>
            <objectCharacteristics>
              <fixity>
                <messageDigestAlgorithm/>
                <messageDigest/>
              </fixity>
              <size>88436192</size>
              <format>
                <formatDesignation>
                  <formatName>pdf</formatName>
                  <formatVersion>Generic PDF</formatVersion>
                </formatDesignation>
              </format>
            </objectCharacteristics>
          </object>
        </xmlData>
      </mdWrap>
    </techMD>
  </amdSec>
  <fileSec>
    <fileGrp USE="">
      <file AMDID="7421" GROUPID="2547" ID="7421">
        <FLocat xlink:href="https://storage.rockarch.org/dcfddb64-8d34-49f9-95fd-b46ce2e1b09f-Appleget_1935.pdf"/>
      </file>
    </fileGrp>
  </fileSec>
  <structMap TYPE="logical">
    <div DMDID="2547" LABEL="Appleget_1935.pdf" ORDER="1" TYPE="item">
      <fptr FILEID="7421"/>
    </div>
  </structMap>
  <structMap TYPE="physical">
    <div DMDID="2547" LABEL="Appleget_1935.pdf" ORDER="1" TYPE="item">
      <fptr FILEID="7421"/>
    </div>
  </structMap>
</mets>

