<mods xmlns="http://www.loc.gov/mods/v3" xmlns:xlink="http://www.w3.org/1999/xlink" xmlns:xsi="http://www.w3.org/2001/XMLSchema-instance" xmlns:xd="http://www.oxygenxml.com/ns/doc/xsl" xsi:schemaLocation="http://www.loc.gov/mods/v3 http://www.loc.gov/standards/mods/v3/mods-3-4.xsd" version="3.4">
  <identifier type="local">LI04875</identifier>
  <titleInfo>
    <title>A legacy continues: the Manley years at Spelman College, 1953-1976.</title>
  </titleInfo>
  <name>
    <namePart>University Press of America</namePart>
    <role>
      <roleTerm type="text" authority="lcnaf">pbl</roleTerm>
    </role>
  </name>
  <name>
    <namePart>Manley, Albert E.</namePart>
    <role>
      <roleTerm type="text" authority="lcnaf">aut</roleTerm>
    </role>
  </name>
  <originInfo>
    <place>
      <placeTerm type="text">Lanham, Md.</placeTerm>
    </place>
    <publisher>University Press of America, 1995</publisher>
    <dateIssued>1995</dateIssued>
  </originInfo>
  <physicalDescription>
    <extent>1 Bound Volumes</extent>
  </physicalDescription>
  <note>Copy 1: Inscribed by author; Copy 2: Autographed</note>
  <subject authority="lcnaf">
    <name type="corporate">
      <namePart>Spelman College</namePart>
    </name>
  </subject>
  <subject authority="lcnaf">
    <name type="personal">
      <namePart>Manley, Albert E.</namePart>
    </name>
  </subject>
  <note type="acquisition">Estate of Laurance S. Rockefeller</note>
  <identifier type="isbn">0-8191-9880-3</identifier>
  <identifier type="lccn">95-1335</identifier>
  <genre>volume</genre>
  <classification>378.758 MAN</classification>
  <genre>volume</genre>
  <classification>378.758 MAN</classification>
</mods>
