<mods xmlns="http://www.loc.gov/mods/v3" xmlns:xlink="http://www.w3.org/1999/xlink" xmlns:xsi="http://www.w3.org/2001/XMLSchema-instance" xmlns:xd="http://www.oxygenxml.com/ns/doc/xsl" xsi:schemaLocation="http://www.loc.gov/mods/v3 http://www.loc.gov/standards/mods/v3/mods-3-4.xsd" version="3.4">
  <identifier type="local">LI09131</identifier>
  <titleInfo>
    <title>On the occasion of Mr. Seep's seventieth birthday.</title>
  </titleInfo>
  <titleInfo type="alternative">
    <title>This is my birthday.</title>
  </titleInfo>
  <name>
    <namePart>Rockefeller, John D. (John Davison)</namePart>
  </name>
  <originInfo>
    <publisher>Titusville, Pa., 1908</publisher>
    <dateIssued>1908</dateIssued>
    <edition>Autograph edition deluxe</edition>
  </originInfo>
  <physicalDescription>
    <extent>1 Bound Volumes</extent>
  </physicalDescription>
  <note>Copy no. 6 of 200, presented with grateful thoughts to John D. Rockefeller..."; Includes: letter from John D. Rockefeller."</note>
  <note type="acquisition">Rockefeller Family Office, Office of JDR, Jr., Personal Library</note>
  <genre>volume</genre>
  <classification>JDR,JR/OFC 2/4/3</classification>
</mods>
