<mods xmlns="http://www.loc.gov/mods/v3" xmlns:xlink="http://www.w3.org/1999/xlink" xmlns:xsi="http://www.w3.org/2001/XMLSchema-instance" xmlns:xd="http://www.oxygenxml.com/ns/doc/xsl" xsi:schemaLocation="http://www.loc.gov/mods/v3 http://www.loc.gov/standards/mods/v3/mods-3-4.xsd" version="3.4">
  <identifier type="local">LI06422</identifier>
  <titleInfo>
    <title>Silver jubilee celebrations, December 1966.</title>
  </titleInfo>
  <name>
    <namePart>Institute of Agriculture (Anand, India)</namePart>
    <role>
      <roleTerm type="text" authority="">aut</roleTerm>
    </role>
  </name>
  <name>
    <namePart>Patel, C. J.</namePart>
    <role>
      <roleTerm type="text" authority="lcnaf">edt</roleTerm>
    </role>
  </name>
  <originInfo>
    <publisher>Anand, India, 1966</publisher>
    <dateIssued>1966</dateIssued>
  </originInfo>
  <physicalDescription>
    <extent>1 Bound Volumes</extent>
  </physicalDescription>
  <relatedItem type="series">
    <titleInfo>
      <title>Vol. 1: Education; Vol. 2: Research</title>
    </titleInfo>
  </relatedItem>
  <subject>
    <name type="corporate">
      <namePart>Institute of Agriculture (Anand, India)</namePart>
    </name>
  </subject>
  <subject authority="lcnaf">
    <name type="personal">
      <namePart>Patel, C. J.</namePart>
    </name>
  </subject>
  <genre>volume</genre>
  <classification>630.7 INS</classification>
</mods>
