<mods xmlns="http://www.loc.gov/mods/v3" xmlns:xlink="http://www.w3.org/1999/xlink" xmlns:xsi="http://www.w3.org/2001/XMLSchema-instance" xmlns:xd="http://www.oxygenxml.com/ns/doc/xsl" xsi:schemaLocation="http://www.loc.gov/mods/v3 http://www.loc.gov/standards/mods/v3/mods-3-4.xsd" version="3.4">
  <identifier type="local">LI00712</identifier>
  <titleInfo>
    <title>A Guide to aural history research.</title>
  </titleInfo>
  <name>
    <namePart>Langlois, W. J.</namePart>
    <role>
      <roleTerm type="text" authority="">edt</roleTerm>
    </role>
  </name>
  <originInfo>
    <dateIssued>1976</dateIssued>
  </originInfo>
  <physicalDescription>
    <extent>1 Bound Volumes</extent>
  </physicalDescription>
  <subject>
    <name type="personal">
      <namePart>Langlois, W. J.</namePart>
    </name>
  </subject>
  <identifier type="oclc">640066412</identifier>
  <genre>volume</genre>
  <classification>780 LAN AS</classification>
</mods>
