<?xml version="1.0" encoding="UTF-8"?>
<mets xmlns="https://www.loc.gov/METS/" xmlns:dc="https://purl.org/dc/elements/1.1/" xmlns:mods="https://www.loc.gov/mods/v3" xmlns:xlink="https://www.w3.org/1999/xlink" xmlns:xsi="https://www.w3.org/2001/XMLSchema-instance" xsi:schemaLocation="https://www.loc.gov/standards/mets/mets.xsd">
  <metsHdr CREATEDATE="2024-10-01 13:03:20 UTC">
    <agent ROLE="CREATOR" TYPE="ORGANIZATION">
      <name>Rockefeller Archive Center</name>
      <note>http://www.rockarch.org</note>
      <note>Produced by ArchivesSpace</note>
    </agent>
  </metsHdr>
  <dmdSec ID="5488">
    <mdWrap MDTYPE="MODS">
      <xmlData>
        <mods version="3.4" xmlns="https://www.loc.gov/mods/v3">
          <mods:titleInfo xmlns:mods="https://www.loc.gov/mods/v3">
            <mods:title xmlns:mods="https://www.loc.gov/mods/v3">China Famine Fund, 1921</mods:title>
          </mods:titleInfo>
          <mods:identifier type="local" xmlns:mods="https://www.loc.gov/mods/v3">af531811-3419-4da4-abfc-2b49fb837dc8</mods:identifier>
          <mods:typeOfResource xmlns:mods="https://www.loc.gov/mods/v3"/>
          <mods:originInfo xmlns:mods="https://www.loc.gov/mods/v3"/>
          <mods:physicalDescription xmlns:mods="https://www.loc.gov/mods/v3"/>
          <mods:note type="originalsloc" xmlns:mods="https://www.loc.gov/mods/v3">94c1c563-e726-45c4-a5fc-0e5889f65da8</mods:note>
          <mods:note displayLabel="Digital object made available by" xmlns:mods="https://www.loc.gov/mods/v3">Rockefeller Archive Center, 15 Dayton Avenue, Sleepy Hollow, 10591, U.S.A. (http://www.rockarch.org)</mods:note>
          <mods:relatedItem displayLabel="resource" type="host" xmlns:mods="https://www.loc.gov/mods/v3">
            <mods:name xmlns:mods="https://www.loc.gov/mods/v3">Laura Spelman Rockefeller Memorial records</mods:name>
            <mods:identifier xmlns:mods="https://www.loc.gov/mods/v3">FA061,xml</mods:identifier>
          </mods:relatedItem>
          <mods:relatedItem displayLabel="component" type="host" xmlns:mods="https://www.loc.gov/mods/v3">
            <mods:name xmlns:mods="https://www.loc.gov/mods/v3">China Famine Fund, 1921</mods:name>
            <mods:identifier xmlns:mods="https://www.loc.gov/mods/v3">3a0648d93daa44eca4352f5ef3dc90cd</mods:identifier>
          </mods:relatedItem>
        </mods>
      </xmlData>
    </mdWrap>
  </dmdSec>
  <amdSec>
    <techMD ID="34675">
      <mdWrap MDTYPE="PREMIS:OBJECT">
        <xmlData>
          <object version="2.2" xmlns="info:lc/xmlns/premis-v2" xsi:schemaLocation="info:lc/xmlns/premis-v2 http://www.loc.gov/standards/premis/v2/premis-v2-2.xsd" xsi:type="file">
            <objectIdentifier xmlns="https://www.loc.gov/METS/">
              <objectIdentifierType>ArchivesSpace identifier</objectIdentifierType>
              <objectIdentifierValue>34675</objectIdentifierValue>
            </objectIdentifier>
            <objectCharacteristics xmlns="https://www.loc.gov/METS/">
              <fixity>
                <messageDigestAlgorithm/>
                <messageDigest/>
              </fixity>
              <size/>
              <format>
                <formatDesignation>
                  <formatName>pdf</formatName>
                  <formatVersion>Generic PDF</formatVersion>
                </formatDesignation>
              </format>
            </objectCharacteristics>
          </object>
        </xmlData>
      </mdWrap>
    </techMD>
  </amdSec>
  <fileSec>
    <fileGrp USE="">
      <file AMDID="34675" GROUPID="5488" ID="34675">
        <FLocat xlink:href="http://storage.rockarch.org/af531811-3419-4da4-abfc-2b49fb837dc8-LSRM_Microfilm_Roll_7_Box8_Folder99.pdf"/>
      </file>
    </fileGrp>
  </fileSec>
  <structMap TYPE="logical">
    <div DMDID="5488" LABEL="China Famine Fund, 1921" ORDER="1" TYPE="item">
      <fptr FILEID="34675"/>
    </div>
  </structMap>
  <structMap TYPE="physical">
    <div DMDID="5488" LABEL="China Famine Fund, 1921" ORDER="1" TYPE="item">
      <fptr FILEID="34675"/>
    </div>
  </structMap>
</mets>

