<?xml version="1.0" encoding="UTF-8"?>
<mets xmlns="http://www.loc.gov/METS/" xmlns:mods="http://www.loc.gov/mods/v3" xmlns:xlink="http://www.w3.org/1999/xlink" xmlns:xsi="http://www.w3.org/2001/XMLSchema-instance" xsi:schemaLocation="http://www.loc.gov/standards/mets/mets.xsd">
  <dmdSec ID="2029">
    <mdWrap MDTYPE="MODS">
      <xmlData>
        <mods version="3.4" xmlns="http://www.loc.gov/mods/v3">
          <mods:titleInfo>
            <mods:title>1940</mods:title>
          </mods:titleInfo>
          <mods:typeOfResource>text</mods:typeOfResource>
          <mods:originInfo>
            <mods:dateCreated>1940</mods:dateCreated>
          </mods:originInfo>
          <mods:language>
            <mods:languageTerm type="code">eng</mods:languageTerm>
          </mods:language>
          <mods:physicalDescription/>
          <mods:note type="originalsloc">1d41ca5b-8c32-4e4d-aaf1-72140d1c086d</mods:note>
          <mods:accessCondition type="restrictionOnAccess">As the author is deceased, the Rockefeller Foundation restriction on the diaries of living officers no longer applies. The Rockefeller Foundation twenty-year embargo has also expired for these materials.</mods:accessCondition>
          <mods:accessCondition type="useAndReproduction">To the extent that the Rockefeller Foundation owns copyright in these materials, it has given the Rockefeller Archive Center the authority to grant permission to cite and publish material from the collection for scholarly purposes.</mods:accessCondition>
          <mods:identifier type="local">dec612eb-59ec-4e02-81a1-98e7d734e57a</mods:identifier>
          <mods:relatedItem displayLabel="resource" type="host">
            <mods:name>Rockefeller Foundation records, officers' diaries, RG 12, F-L</mods:name>
            <mods:identifier>FA392.xml</mods:identifier>
          </mods:relatedItem>
          <mods:relatedItem displayLabel="component" type="host">
            <mods:name>1940</mods:name>
            <mods:identifier>ref380_l2r</mods:identifier>
          </mods:relatedItem>
        </mods>
      </xmlData>
    </mdWrap>
  </dmdSec>
  <amdSec>
    <techMD ID="2029">
      <mdWrap MDTYPE="PREMIS:OBJECT">
        <xmlData>
          <object version="2.2" xmlns="info:lc/xmlns/premis-v2" xsi:schemaLocation="info:lc/xmlns/premis-v2 http://www.loc.gov/standards/premis/v2/premis-v2-2.xsd" xsi:type="file">
            <objectIdentifier>
              <objectIdentifierType>ArchivesSpace identifier</objectIdentifierType>
              <objectIdentifierValue>2029</objectIdentifierValue>
            </objectIdentifier>
            <objectCharacteristics>
              <fixity>
                <messageDigestAlgorithm/>
                <messageDigest/>
              </fixity>
              <size/>
              <format>
                <formatDesignation>
                  <formatName/>
                  <formatVersion/>
                </formatDesignation>
              </format>
            </objectCharacteristics>
          </object>
        </xmlData>
      </mdWrap>
    </techMD>
  </amdSec>
  <fileSec>
    <fileGrp USE="Service-Edited">
      <file AMDID="2029" GROUPID="2029" ID="2029">
        <FLocat xlink:href="http://storage.rockarch.org/dec612eb-59ec-4e02-81a1-98e7d734e57a-rac_rfdiaries_12-2_grant_1937-1955_003.pdf"/>
      </file>
    </fileGrp>
  </fileSec>
  <structMap TYPE="logical">
    <div DMDID="2029" LABEL="1940" ORDER="1" TYPE="item">
      <fptr FILEID="2029"/>
    </div>
  </structMap>
  <structMap TYPE="physical">
    <div DMDID="2029" LABEL="1940" ORDER="1" TYPE="item">
      <fptr FILEID="2029"/>
    </div>
  </structMap>
</mets>

